apsitv27_mysql/Dockerfile
apsitv27_mysql/__init__.py
apsitv27_mysql/entrypoint.sh
apsitv27_mysql/install_docker.sh
apsitv27_mysql/main.py
apsitv27_mysql-2.0.5.dist-info/METADATA
apsitv27_mysql-2.0.5.dist-info/WHEEL
apsitv27_mysql-2.0.5.dist-info/entry_points.txt
apsitv27_mysql-2.0.5.dist-info/top_level.txt
apsitv27_mysql-2.0.5.dist-info/RECORD
